spida/__init__.py
spida/stable_diffusion.py
spida/data/config.json
spida/utils/__init__.py
spida/utils/img.py
spida/utils/misc.py
spida/utils/net.py
spida-0.3.9.dist-info/LICENSE
spida-0.3.9.dist-info/METADATA
spida-0.3.9.dist-info/WHEEL
spida-0.3.9.dist-info/top_level.txt
spida-0.3.9.dist-info/RECORD
