Metadata-Version: 2.1
Name: spida
Version: 0.3.9
Summary: A Stable Diffusion API Wrapper for AUTOMATIC1111/stable-diffusion-webui
Home-page: https://github.com/h2see/spida
Author: h2see
License: MIT
Classifier: License :: OSI Approved :: MIT License
Classifier: Programming Language :: Python :: 3.10
Classifier: Operating System :: OS Independent
Requires-Python: >=3.10, <3.11
License-File: LICENSE
Requires-Dist: certifi (==2023.5.7)
Requires-Dist: charset-normalizer (==3.1.0)
Requires-Dist: contourpy (==1.0.7)
Requires-Dist: cycler (==0.11.0)
Requires-Dist: fonttools (==4.39.4)
Requires-Dist: idna (==3.4)
Requires-Dist: kiwisolver (==1.4.4)
Requires-Dist: matplotlib (==3.7.1)
Requires-Dist: numpy (==1.24.3)
Requires-Dist: packaging (==23.1)
Requires-Dist: Pillow (==9.5.0)
Requires-Dist: pyparsing (==3.0.9)
Requires-Dist: python-dateutil (==2.8.2)
Requires-Dist: requests (==2.31.0)
Requires-Dist: six (==1.16.0)
Requires-Dist: urllib3 (==2.0.2)
